pynav2/__init__.py
pynav2/browser.py
pynav2/useragent.py
pynav2-2.1.dist-info/LICENSE
pynav2-2.1.dist-info/METADATA
pynav2-2.1.dist-info/WHEEL
pynav2-2.1.dist-info/top_level.txt
pynav2-2.1.dist-info/RECORD
