Metadata-Version: 2.1
Name: pynav2
Version: 2.1
Summary: Headless programmatic web browser on top of Requests and Beautiful Soup
Home-page: https://github.com/sloft/pynav2/
Author: sloft
Author-email: nomail@example.com
License: GNU Lesser General Public License Version 3 (LGPLv3)
Download-URL: https://pypi.org/project/pynav2/#files
Keywords: programmatic,web,browser
Platform: UNKNOWN
Classifier: Programming Language :: Python :: 3.4
Classifier: Programming Language :: Python :: 3.5
Classifier: Programming Language :: Python :: 3.6
Classifier: Programming Language :: Python :: 3.7
Classifier: Operating System :: OS Independent
Classifier: License :: OSI Approved :: GNU Library or Lesser General Public License (LGPL)
Classifier: Development Status :: 4 - Beta
Classifier: Environment :: Console
Classifier: Topic :: Internet
Classifier: Intended Audience :: Developers
Classifier: Topic :: Internet :: WWW/HTTP
Classifier: Topic :: Internet :: WWW/HTTP :: Browsers
Classifier: Topic :: Internet :: WWW/HTTP :: Indexing/Search
Classifier: Topic :: Internet :: WWW/HTTP :: Site Management
Classifier: Topic :: Internet :: WWW/HTTP :: Site Management :: Link Checking
Classifier: Topic :: Software Development :: Libraries
Classifier: Topic :: Software Development :: Libraries :: Python Modules
Requires-Python: >=3.4
Requires-Dist: requests
Requires-Dist: beautifulsoup4
